better_ffmpeg_progress/__init__.py
better_ffmpeg_progress/better_ffmpeg_progress.py
better_ffmpeg_progress/enums.py
better_ffmpeg_progress/exceptions.py
better_ffmpeg_progress/progress_bars.py
better_ffmpeg_progress/terminate_process.py
better_ffmpeg_progress/utils.py
better_ffmpeg_progress-4.0.1.dist-info/LICENSE
better_ffmpeg_progress-4.0.1.dist-info/METADATA
better_ffmpeg_progress-4.0.1.dist-info/WHEEL
better_ffmpeg_progress-4.0.1.dist-info/top_level.txt
better_ffmpeg_progress-4.0.1.dist-info/RECORD
