Metadata-Version: 2.1
Name: better-ffmpeg-progress
Version: 4.0.1
Summary: Run FFmpeg & see percentage progress + ETA.
Home-page: https://github.com/CrypticSignal/better-ffmpeg-progress
Author: GitHub.com/CrypticSignal
Author-email: theaudiophile@outlook.com
Keywords: ffmpeg,progress
Classifier: Programming Language :: Python :: 3
Classifier: License :: OSI Approved :: MIT License
Classifier: Operating System :: OS Independent
Requires-Python: >=3.7
License-File: LICENSE
Requires-Dist: psutil
Requires-Dist: requests
Requires-Dist: rich
Requires-Dist: tqdm
